mysdk/__init__.py
mysdk/apihelper.py
mysdk/urls.py
mysdk/utils.py
mysdk/version.py
pyMyShareSDK-0.0.3.dist-info/LICENSE
pyMyShareSDK-0.0.3.dist-info/METADATA
pyMyShareSDK-0.0.3.dist-info/WHEEL
pyMyShareSDK-0.0.3.dist-info/top_level.txt
pyMyShareSDK-0.0.3.dist-info/RECORD
