Metadata-Version: 2.1
Name: pyMyShareSDK
Version: 0.0.3
Summary: Python SDK for MyShare API 
Home-page: https://github.com/LeanderGangso/pyMyShareAPI
Author: LeanderGangso
Author-email: Leander.Gangso98@gmail.com
License: MIT
Download-URL: https://github.com/LeanderGangso/pyMyShareAPI/archive/v0.0.3.tar.gz
Keywords: python myshare sdk api tools
Platform: UNKNOWN
Classifier: Development Status :: 1 - Planning
Classifier: License :: OSI Approved :: MIT License
Classifier: Operating System :: OS Independent
Classifier: Intended Audience :: Developers
Classifier: Topic :: Software Development :: Libraries :: Python Modules
Classifier: Programming Language :: Python
Classifier: Programming Language :: Python :: 3.6
Classifier: Programming Language :: Python :: 3.7
Classifier: Programming Language :: Python :: 3.8
Classifier: Programming Language :: Python :: 3.9
Requires-Python: >=3.6
Requires-Dist: requests
Provides-Extra: dev
Requires-Dist: pytest (==6.2.2) ; extra == 'dev'
Requires-Dist: check-manifest (==0.46) ; extra == 'dev'
